{
    "monsters": [
        {
            "name": "Mr Sally's Ghost",
            "location": "Isle of Moroha",
            "level": 25,
            "hp": 14811,
            "ac": 375,
            "exp": 1400,
            "aggro_range": 8,
            "move_speed": 1.5,
            "damage": 152,
            "atk_speed": 1,
            "atk_range": 1,
            "is_boss": true,
            "spawn_x": 250,
            "spawn_y": 250,
            "respawn_time_sec": 900,
            "loot_table": [
                {
                    "name": "Skullthumper",
                    "chance": 0.15
                },
                {
                    "name": "Quartz Staff",
                    "chance": 0.15
                },
                {
                    "name": "Sturdy Hammer",
                    "chance": 0.15
                },
                {
                    "name": "Reinforced Knuckle",
                    "chance": 0.15
                },
                {
                    "name": "Poison Dagger",
                    "chance": 0.15
                },
                {
                    "name": "Magic Moon Wand",
                    "chance": 0.15
                },
                {
                    "name": "Distracting Lute",
                    "chance": 0.15
                }
            ],
            "img_url": "https://static.wikia.nocookie.net/yugen-saga/images/c/cd/Mr_Sally%27s_Ghost.png/revision/latest?cb=20230619220840"
        }
    ]
}